# 锁

## 锁分类
7大类：
* 偏向锁/轻量级锁/重量级锁
* 可重入锁/非可重入锁
* 共享锁/独占锁
* 公平锁/非公平锁
* 悲观锁/乐观锁
* 自旋锁/非自旋锁
* 可中断锁/不可中断锁


### 偏向锁/轻量级锁/重量级锁
这三种锁特指synchronized锁的状态，通过对象头中的mark word来表明锁的状态。
* 偏向锁
大多数情况下，锁不存在竞争，没有必要上锁，只需要打个标记就行，偏向锁的思想；一个对象初始化后，还没有任何线程来获取它的锁时，那么它就是可偏向的，当有第一个线程来访问它并尝试获取锁的时候，它将这个线程记录下来，以后如果尝试获取锁的线程正是偏向锁的拥有者，直接获取锁，开销小，性能最好。

* 轻量级锁
synchronized中的代码是被多个线程交替执行的，不是同时执行的，不存在实际的竞争或只有短时间的锁竞争，用CAS就阔以解决，没有必要使用完全互斥的重量级锁。轻量级锁是指当前锁原来是偏向锁的时候，被另一个线程访问，说明存在竞争，那么偏向锁升级为轻量锁，线程会通过自旋的形式获取锁，而不会陷入阻塞。

* 重量级锁
重量级锁是互斥锁，利用操作系统同步机制实现，开销相对比较大；多个线程直接有实际竞争，且锁竞争时间长的时候，轻量级锁不能满足需求，锁就会膨胀为重量级锁。重量级锁会让其他申请却拿不到锁的线程进入阻塞状态。

综上，偏向锁性能最好，可以避免执行CAS操作。而轻量级锁则利用自旋和CAS操作避免了重量级锁带来的线程阻塞和唤醒，性能中等。重量锁则会把获取不到的锁的线程阻塞，性能差。 

### 可重入锁
指线程当前已经持有这把锁，能在不释放这把锁的情况下，再次获取锁。同理不可重入，要释放锁后才能进行再次尝试获取。典型的ReentrantLock,synchronized

### 共享锁/独占锁
同一把锁可以让多个线程同时获得，独占锁只能同时被一个线程获取。读写锁，读锁是共享，写锁是独占。

### 公平锁/非公平锁
拿不到锁的线程排队，先来先得；非公平可以插队。

### 悲观锁/乐观锁
悲观锁在获取资源钱，必须先拿到锁，以便独占的状态，操作资源的时候，其他线程拿不到锁；乐观锁洽洽相反，并不要求获取资源前拿到锁，不会锁住资源，利用CAS操作，完成对资源的操作。

### 自旋锁/非自旋
自旋锁的理念是如果线程现在拿不到锁，并不直接陷入阻塞或者释放 CPU 资源，而是开始利用循环，不停地尝试获取锁，这个循环过程被形象地比喻为“自旋”，就像是线程在“自我旋转”。相反，非自旋锁的理念就是没有自旋的过程，如果拿不到锁就直接放弃，或者进行其他的处理逻辑，例如去排队、陷入阻塞等。

### 可中断/不可中断
java中synchronized关键字修饰的锁代表不可中断，一旦线程申请了锁，没有回头路，只能等到拿到锁以后，才能进行其他的逻辑处理；而ReentrantLock可中断，使用lockInterruptibly获取锁的过程中，突然不想获取了，可以中断之后，去做其他的事情，不需要一直等待获取到锁才离开。

## 乐观锁与悲观锁的本质
### 悲观锁
悲观锁比较悲观，它认为如果不锁住这个资源，别的线程就会来争抢，就会造成数据结果错误，所以悲观锁为了确保结果的正确性，会在每次获取并修改数据时，都把数据锁住，让其他线程无法访问该数据，这样就可以确保数据内容万无一失。
### 乐观锁
乐观锁比较乐观，认为自己在操作资源的时候不会有其他线程来干扰，所以并不会锁住被操作对象，不会不让别的线程来接触它，同时，为了确保数据正确性，在更新之前，会去对比在我修改数据期间，数据有没有被其他线程修改过：如果没被修改过，就说明真的只有我自己在操作，那我就可以正常的修改数据；如果发现数据和我一开始拿到的不一样了，说明其他线程在这段时间内修改过数据，那说明我迟了一步，所以我会放弃这次修改，并选择报错、重试等策略。

### 典型案例
* 悲观锁：synchronized关键字和Lock接口
* 乐观锁：原子类
* 大喜大悲：数据库

### 使用场景
* 悲观锁：适合并发写入多，临界区代码复杂、竞争激烈等场景，避免大量无用的反复尝试等消耗
* 乐观锁：适用于大部分读取，少部分写的场景，也适合读写都多，但并发不激烈的场景。

## 如何看到synchronized背后的“monitor"锁

### 获取和释放锁的时机
最简单同步方式：利用synchronized关键字修饰代码块或修饰一个方法，每个java对象都可以用做一个实现同步的锁，内置锁，获得monitor锁的唯一途径就是进入这个锁保护的同步代码块或同步方法，进入之前，自动获取锁，无论正常退出还是异常都会自动释放锁。
```java
public synchronized void method() {
    method body
}
//上面代码等效下面
public void method() {
    this.intrinsicLock.lock();
    try{
        method body
    }
    finally {
        this.intrinsicLock.unlock();
    }
}
```
### javap查看反汇编
#### 同步代码块
```java
public class SynTest {
    public void synBlock() {
        synchronized (this) {
            System.out.println("lagou");
        }
    }
}

  public void synBlock();
    descriptor: ()V
    flags: ACC_PUBLIC
    Code:
      stack=2, locals=3, args_size=1
         0: aload_0
         1: dup
         2: astore_1
         3: monitorenter
         4: getstatic     #2                  // Field java/lang/System.out:Ljava/io/PrintStream;
         7: ldc           #3                      // String lagou
         9: invokevirtual #4               // Method java/io/PrintStream.println:(Ljava/lang/String;)V
        12: aload_1
        13: monitorexit
        14: goto          22
        17: astore_2
        18: aload_1
        19: monitorexit
        20: aload_2
        21: athrow
        22: return
```
>我们可以看到synchronized代码块实际上多了monitorenter和monitorexit指令，
* monitorenter
  执行monitorenter的线程尝试获取monitor的所有权，
  a. 如果该monitor的计数为0，该线程获得monitor，将计数设置为1，该线程就是monitor的所有者   
  b.如果线程已经拥有这个monitor，则她将重新进入，累加计数
  c.如果其他线程已经拥有这个monitor，这个线程将会被阻塞直到monitor的计数变为0，当前线程会再次尝试获取这个monitor
* monitorexit
  monitorexit 的作用是将 monitor 的计数器减 1，直到减为 0 为止。代表这个 monitor 已经被释放了，已经没有任何线程拥有它了，也就代表着解锁，所以，其他正在等待这个 monitor 的线程，此时便可以再次尝试获取这个 monitor 的所有权。

#### 同步方法

```java
public synchronized void synMethod() {
 
}

  public synchronized void synMethod();
    descriptor: ()V
    flags: ACC_PUBLIC, ACC_SYNCHRONIZED
    Code:
      stack=0, locals=1, args_size=1
         0: return
      LineNumberTable:
        line 16: 0
```
同步代码块使用monitorenter和monitorexit指令实现；而synchronized方法，则是会有一个ACC_SYNCHRONIZED标志，线程访问某方法时会检查这个标志，有则获取monitor锁，开始执行方法，最后释放锁。

### jdk1.5后，jvm对内置锁优化
包括自适应的自旋、锁消除、锁粗化、轻量级锁、偏向锁等；
* jdk1.6引入的自适应的自旋锁，来解决长时间自旋的问题，自旋时间不再固定，根据近期自旋尝试的成功率、失败率以及当前锁的拥有者的状态多种因素来共同确定。自旋默认10次，通过-XX：PreBlockSpin设置
* 锁消除：
```java
@Override
public synchronized StringBuffer append(Object obj) {
    toStringCache = null;
    super.append(String.valueOf(obj));
    return this;
}
```
但是在大多数情况下，它只会在一个线程内被使用，如果编译器能确定这个 StringBuffer 对象只会在一个线程内被使用，就代表肯定是线程安全的，那么我们的编译器便会做出优化，把对应的 synchronized 给消除，省去加锁和解锁的操作，以便增加整体的效率。  

* 锁粗化
```java
public void lockCoarsening() {
    synchronized (this) {
        //do something
    }
    synchronized (this) {
        //do something
    }
    synchronized (this) {
        //do something
    }
}

```
那么其实这种释放和重新获取锁是完全没有必要的，如果我们把同步区域扩大，也就是只在最开始加一次锁，并且在最后直接解锁，那么就可以把中间这些无意义的解锁和加锁的过程消除，相当于是把几个 synchronized 块合并为一个较大的同步块。这样做的好处在于在线程执行这些代码时，就无须频繁申请与释放锁了，这样就减少了性能开销
这里的锁粗化不适用于循环的场景，仅适用于非循环的场景。
* 偏向锁/轻量级锁/重量级锁



## synchronize与Lock如何选择

### 相同点
* synchronized和lock都是用来保护资源线程安全的
* 都可以保证可见性（happens-before)
* 都可以重入

### 不同点

* 用法不同
synchronized关键字可以用在方法上(锁对象为this)，新建同步代码块并且自定义monitor锁对象，加解锁是隐式的；而Lock接口必须显示调用Lock锁对象加锁lock()和解锁unlock()，一般在finally块中确保用unlock释放，防止发生死锁

* 加解锁顺序不同
Lock锁而言，lock可以不用按照加锁顺序的反序解锁；synchronized解锁的顺序必须和加锁顺序完全相反，必须按照synchronized嵌套顺序

* synchronized 锁不够灵活
一旦 synchronized 锁已经被某个线程获得了，此时其他线程如果还想获得，那它只能被阻塞，直到持有锁的线程运行完毕或者发生异常从而释放这个锁。  
Lock锁在等待时可以如果使用的是 lockInterruptibly 方法，那么如果觉得等待的时间太长了不想再继续等待，可以中断退出，也可以用 tryLock() 等方法尝试获取锁，如果获取不到锁也可以做别的事，更加灵活。

* synchronized只能同时被一个线程拥有，但是Lock锁没有这个限制，读写锁中的读锁可以被多个线程持有，而synchronize的不行
* 原理不同，synchronized是内置锁，由JVM实现获取和释放锁；Lock根据实现不同，不同的原理例如ReentrantLock由AQS实现

* 是否可以设置公平；Lock可以根据需求设置；synchronizede不行
* 性能区别：1.5前，synchronized性能较低，1.6后进行了性能优化

### 如何选择
* 如果能不用最好既不使用 Lock 也不使用 synchronized。因为在许多情况下你可以使用 java.util.concurrent 包中的机制，它会为你处理所有的加锁和解锁操作，也就是推荐优先使用工具类来加解锁。
* 如果 synchronized 关键字适合你的程序， 那么请尽量使用它，这样可以减少编写代码的数量，减少出错的概率。因为一旦忘记在 finally 里 unlock，代码可能会出很大的问题，而使用 synchronized 更安全。
* 如果特别需要 Lock 的特殊功能，比如尝试获取锁、可中断、超时功能等，才使用 Lock。

## Lock有哪几个常用的方法
```java
public interface Lock {
    void lock();
    void lockInterruptibly() throws InterruptedException;
    boolean tryLock();
    boolean tryLock(long time, TimeUnit unit) throws InterruptedException;
    void unlock();
    Condition newCondition();
}
```
* lock()最基础获取锁的方法，如果锁已经被其他线程获取，则进行等待
* tryLock() 用来尝试获取锁，如果当前锁没有被其他线程占用，则获取成功，返回 true，否则返回 false，代表获取锁失败。相比于 lock()，这样的方法显然功能更强大，我们可以根据是否能获取到锁来决定后续程序的行为。立即返回，不会一直等待
* tryLock() 的重载方法是 tryLock(long time, TimeUnit unit)，这个方法和 tryLock() 很类似，区别在于 tryLock(long time, TimeUnit unit) 方法会有一个超时时间，在拿不到锁时会等待一定的时间，如果在时间期限结束后，还获取不到锁，就会返回 false；如果一开始就获取锁或者等待期间内获取到锁，则返回 true。
这个方法解决了 lock() 方法容易发生死锁的问题，使用 tryLock(long time, TimeUnit unit) 时，在等待了一段指定的超时时间后，线程会主动放弃这把锁的获取，避免永久等待；在等待的期间，也可以随时中断线程，这就避免了死锁的发生。
*  lockInterruptibly()可以让程序更灵活，可以在获取锁的同时，保持对中断的响应;除非当前线程在获取锁期间被中断，否则便会一直尝试获取直到获取到为止。
*  unlock()用于解锁

## 公平锁与非公平锁
||优势|劣势|
|---|---|---|
|公平锁|各线程公平平等，每个线程在等待一段时间后，总有机会执行|更慢，吞吐量小|
|非公平锁|更快，吞吐量更大|有可能产生线程饥饿，就是某些线程长时间内始终得不到执行|

## 读写锁ReadWriteLock
我们在使用读写锁时遵守下面的获取规则：

* 如果有一个线程已经占用了读锁，则此时其他线程如果要申请读锁，可以申请成功。

* 如果有一个线程已经占用了读锁，则此时其他线程如果要申请写锁，则申请写锁的线程会一直等待释放读锁，因为读写不能同时操作。

* 如果有一个线程已经占用了写锁，则此时其他线程如果申请写锁或者读锁，都必须等待之前的线程释放写锁，同样也因为读写不能同时，并且两个线程不应该同时写。

所以我们用一句话总结：要么是一个或多个线程同时有读锁，要么是一个线程有写锁，但是两者不会同时出现。也可以总结为：读读共享、其他都互斥（写写互斥、读写互斥、写读互斥）。

## 读锁插队，读写锁升降级
对锁进行设置非公平即可插队
```java
//公平锁
ReentrantReadWriteLock reentrantReadWriteLock = new ReentrantReadWriteLock(true);
//非公平
ReentrantReadWriteLock reentrantReadWriteLock = new ReentrantReadWriteLock(false);
```

### 锁升降级
```java
public class CachedData {
 
    Object data;
    volatile boolean cacheValid;
    final ReentrantReadWriteLock rwl = new ReentrantReadWriteLock();
 
    void processCachedData() {
        rwl.readLock().lock();
        if (!cacheValid) {
            //在获取写锁之前，必须首先释放读锁。
            rwl.readLock().unlock();
            rwl.writeLock().lock();
            try {
                //这里需要再次判断数据的有效性,因为在我们释放读锁和获取写锁的空隙之内，可能有其他线程修改了数据。
                if (!cacheValid) {
                    data = new Object();
                    cacheValid = true;
                }
                //在不释放写锁的情况下，直接获取读锁，这就是读写锁的降级。
                rwl.readLock().lock();
            } finally {
                //释放了写锁，但是依然持有读锁
                rwl.writeLock().unlock();
            }
        }
 
        try {
            System.out.println(data);
        } finally {
            //释放读锁
            rwl.readLock().unlock();
        }
    }
}
```


### 对于ReentrantReadWriteLock
* 插队策略
  * 公平策略下，只有队里线程已经在排队，不允许插队
  * 非公平锁
    * 如果允许读锁插队，读锁可以同时被多个线程持有，可能读锁一直不能完全释放，导致写锁一直等待，防止饥饿：在等待队列的头结点尝试获取写锁的线程的时候，不允许读锁插队
    * 写锁可以随时插队，写锁并不容易插队成功，只有当前没有任何其他线程持有读写锁的时候，才能插队成功；一旦插队失败进入等待队列，很难出现饥饿的情况，允许写锁提高允许效率
* 升降级策略：只能从写锁降级读锁，不能从读锁升级成写锁。


[美团java](https://mp.weixin.qq.com/s?__biz=MjM5NjQ5MTI5OA==&mid=2651749434&idx=3&sn=5ffa63ad47fe166f2f1a9f604ed10091&chksm=bd12a5778a652c61509d9e718ab086ff27ad8768586ea9b38c3dcf9e017a8e49bcae3df9bcc8&scene=21#wechat_redirect)